rmwrapper/RedditMetricsWrapper.py
rmwrapper/__init__.py
rmwrapper-0.0.1.dist-info/LICENSE
rmwrapper-0.0.1.dist-info/METADATA
rmwrapper-0.0.1.dist-info/WHEEL
rmwrapper-0.0.1.dist-info/top_level.txt
rmwrapper-0.0.1.dist-info/RECORD
