Metadata-Version: 2.1
Name: rmwrapper
Version: 0.0.1
Summary: Minimal wrapper for Redditmetrics
Home-page: https://github.com/d9x33/rmwrapper
Author: ad044
Author-email: 
License: UNKNOWN
Platform: UNKNOWN
Classifier: Programming Language :: Python :: 3
Classifier: License :: OSI Approved :: MIT License
Classifier: Operating System :: OS Independent
Requires-Python: >=3.6
